{
  "id": "offload-architecture",
  "title": "Offload Architecture Tour",
  "description": "A guided walkthrough of Offload, a parallel test runner written in Rust with pluggable execution providers and test frameworks.",
  "version": "1.0.0",
  "steps": [
    {
      "id": "overview",
      "title": "Offload at a Glance",
      "description": "Offload is a flexible parallel test runner by Imbue AI. It fans out test execution across multiple sandboxes (local processes or remote Modal environments) with automatic retry, flaky test detection, and JUnit XML reporting. The codebase follows a layered architecture: CLI entry point, configuration, providers, frameworks, orchestrator, and reporting.",
      "focusDirectory": "",
      "colorMode": "fileTypes"
    },
    {
      "id": "entry-point",
      "title": "CLI Entry Point",
      "description": "main.rs is the CLI entry point using clap for argument parsing. It handles subcommands: run (execute tests), collect (discover tests), validate (check config), init (generate config), and logs (view results). The lib.rs module re-exports the public API surface.",
      "focusDirectory": "src",
      "colorMode": "fileTypes",
      "highlightLayers": [
        {
          "id": "cli-entry",
          "name": "CLI Entry & Library Root",
          "color": "#3b82f6",
          "items": [
            { "path": "src/main.rs", "type": "file" },
            { "path": "src/lib.rs", "type": "file" }
          ],
          "opacity": 0.8,
          "renderStrategy": "border"
        }
      ]
    },
    {
      "id": "configuration",
      "title": "Configuration Layer",
      "description": "The config module parses offload.toml files using TOML deserialization with environment variable expansion (${VAR} and ${VAR:-default} syntax). config.rs handles loading and validation, while config/schema.rs defines the typed configuration structs: OffloadConfig, ProviderConfig, FrameworkConfig, GroupConfig, and ReportConfig.",
      "focusDirectory": "src",
      "colorMode": "fileTypes",
      "highlightLayers": [
        {
          "id": "config-layer",
          "name": "Configuration",
          "color": "#f59e0b",
          "items": [
            { "path": "src/config.rs", "type": "file" },
            { "path": "src/config", "type": "directory" }
          ],
          "opacity": 0.8,
          "renderStrategy": "border"
        },
        {
          "id": "config-files",
          "name": "Config Files",
          "color": "#a855f7",
          "items": [
            { "path": "offload.toml", "type": "file" },
            { "path": "offload-pytest-default.toml", "type": "file" },
            { "path": "offload-cargo-modal.toml", "type": "file" }
          ],
          "opacity": 0.6,
          "renderStrategy": "border"
        }
      ]
    },
    {
      "id": "providers",
      "title": "Execution Providers",
      "description": "Providers abstract sandbox lifecycle management. The provider trait defines prepare, create, exec, destroy, and download operations. Three implementations exist: Local (child processes), Default (custom shell commands with placeholder substitution), and Modal (simplified Modal sandbox integration). The connector module handles the low-level process spawning shared across providers.",
      "focusDirectory": "src",
      "colorMode": "fileTypes",
      "highlightLayers": [
        {
          "id": "provider-layer",
          "name": "Providers",
          "color": "#10b981",
          "items": [
            { "path": "src/provider.rs", "type": "file" },
            { "path": "src/provider", "type": "directory" },
            { "path": "src/connector.rs", "type": "file" }
          ],
          "opacity": 0.8,
          "renderStrategy": "border"
        },
        {
          "id": "modal-script",
          "name": "Modal Script",
          "color": "#06b6d4",
          "items": [
            { "path": "scripts/modal_sandbox.py", "type": "file" }
          ],
          "opacity": 0.6,
          "renderStrategy": "border"
        }
      ]
    },
    {
      "id": "frameworks",
      "title": "Test Frameworks",
      "description": "Frameworks handle test discovery and command generation. Each framework implements discover (list test IDs) and build_command (construct execution commands). Pytest runs --collect-only for discovery, Cargo uses nextest list, Vitest uses --reporter=json, and Default uses custom shell commands. The framework trait also defines test_id_format for matching discovered IDs to JUnit XML results.",
      "focusDirectory": "src/framework",
      "colorMode": "fileTypes",
      "highlightLayers": [
        {
          "id": "framework-layer",
          "name": "Framework Implementations",
          "color": "#ef4444",
          "items": [
            { "path": "src/framework.rs", "type": "file" },
            { "path": "src/framework/pytest.rs", "type": "file" },
            { "path": "src/framework/cargo.rs", "type": "file" },
            { "path": "src/framework/default.rs", "type": "file" },
            { "path": "src/framework/vitest.rs", "type": "file" }
          ],
          "opacity": 0.8,
          "renderStrategy": "border"
        }
      ]
    },
    {
      "id": "orchestrator",
      "title": "Orchestrator: The Engine",
      "description": "The orchestrator is the heart of Offload. It coordinates the entire test run: scheduler.rs partitions tests into batches using LPT scheduling (or round-robin fallback), pool.rs manages a pool of sandboxes, spawn.rs handles concurrent batch execution across sandboxes, and runner.rs ties it all together -- driving the discover-schedule-execute-collect loop with retry logic and fail-fast support.",
      "focusDirectory": "src/orchestrator",
      "colorMode": "fileTypes",
      "highlightLayers": [
        {
          "id": "orchestrator-layer",
          "name": "Orchestrator Core",
          "color": "#8b5cf6",
          "items": [
            { "path": "src/orchestrator.rs", "type": "file" },
            { "path": "src/orchestrator/runner.rs", "type": "file" },
            { "path": "src/orchestrator/scheduler.rs", "type": "file" },
            { "path": "src/orchestrator/pool.rs", "type": "file" },
            { "path": "src/orchestrator/spawn.rs", "type": "file" }
          ],
          "opacity": 0.8,
          "renderStrategy": "border"
        }
      ]
    },
    {
      "id": "reporting",
      "title": "Reporting & Tracing",
      "description": "The report module handles JUnit XML parsing and generation. After each batch, results are matched back to discovered test IDs using test_id_format. The trace module emits Chrome Trace Event JSON (Perfetto-compatible) for visualizing execution timelines -- showing local phases, orchestrator scheduling, and per-sandbox batch execution. The bundled module manages extraction of embedded scripts (like modal_sandbox.py) from the binary.",
      "focusDirectory": "src",
      "colorMode": "fileTypes",
      "highlightLayers": [
        {
          "id": "report-layer",
          "name": "Reporting",
          "color": "#f97316",
          "items": [
            { "path": "src/report.rs", "type": "file" },
            { "path": "src/report", "type": "directory" }
          ],
          "opacity": 0.8,
          "renderStrategy": "border"
        },
        {
          "id": "support-layer",
          "name": "Tracing & Bundled Scripts",
          "color": "#ec4899",
          "items": [
            { "path": "src/trace.rs", "type": "file" },
            { "path": "src/bundled.rs", "type": "file" }
          ],
          "opacity": 0.7,
          "renderStrategy": "border"
        }
      ]
    },
    {
      "id": "full-picture",
      "title": "The Full Picture",
      "description": "Offload's architecture flows top-down: CLI parses args, config loads and validates the TOML file, the orchestrator discovers tests via the framework, schedules batches, creates sandboxes via the provider, executes tests, collects JUnit results, handles retries, and produces a final report. The examples/ directory contains sample Dockerfiles and test suites for integration testing Offload itself.",
      "focusDirectory": "",
      "colorMode": "fileTypes",
      "highlightLayers": [
        {
          "id": "core-src",
          "name": "Source Code",
          "color": "#3b82f6",
          "items": [
            { "path": "src", "type": "directory" }
          ],
          "opacity": 0.5,
          "renderStrategy": "border"
        },
        {
          "id": "testing-infra",
          "name": "Tests & Examples",
          "color": "#10b981",
          "items": [
            { "path": "tests", "type": "directory" },
            { "path": "examples", "type": "directory" }
          ],
          "opacity": 0.5,
          "renderStrategy": "border"
        },
        {
          "id": "project-config",
          "name": "Project Configuration",
          "color": "#f59e0b",
          "items": [
            { "path": "Cargo.toml", "type": "file" },
            { "path": "offload.toml", "type": "file" }
          ],
          "opacity": 0.5,
          "renderStrategy": "border"
        }
      ]
    }
  ]
}
